cmq/__init__.py
cmq/aws/__init__.py
cmq/aws/aws.py
cmq/aws/resource/__init__.py
cmq/aws/resource/address.py
cmq/aws/resource/alarm.py
cmq/aws/resource/cloudformation.py
cmq/aws/resource/cloudtrail.py
cmq/aws/resource/dynamodb.py
cmq/aws/resource/ec2.py
cmq/aws/resource/elasticache.py
cmq/aws/resource/elasticache_parameter_group.py
cmq/aws/resource/elasticache_replication_group.py
cmq/aws/resource/elasticache_subnet_group.py
cmq/aws/resource/function.py
cmq/aws/resource/keyspace.py
cmq/aws/resource/keyspace_table.py
cmq/aws/resource/kinesis.py
cmq/aws/resource/kms.py
cmq/aws/resource/kms_alias.py
cmq/aws/resource/log.py
cmq/aws/resource/log_event.py
cmq/aws/resource/log_stream.py
cmq/aws/resource/metric.py
cmq/aws/resource/rds.py
cmq/aws/resource/rds_parameter.py
cmq/aws/resource/rds_parameter_group.py
cmq/aws/resource/region.py
cmq/aws/resource/resource_explorer.py
cmq/aws/resource/resource_group.py
cmq/aws/resource/role.py
cmq/aws/resource/route53.py
cmq/aws/resource/s3.py
cmq/aws/resource/s3_object.py
cmq/aws/resource/secret.py
cmq/aws/resource/security_group.py
cmq/aws/resource/sns.py
cmq/aws/resource/sqs.py
cmq/aws/resource/user.py
cmq/aws/resource/user_key.py
cmq/aws/resource/vpc.py
cmq/aws/session/__init__.py
cmq/aws/session/profile.py
cmq/base.py
cmq/base.pyi
cmq/cli.py
cmq/iterator.py
cmq/plugin.py
cmq-0.9.1.dist-info/METADATA
cmq-0.9.1.dist-info/WHEEL
cmq-0.9.1.dist-info/entry_points.txt
cmq-0.9.1.dist-info/licenses/LICENSE
cmq-0.9.1.dist-info/RECORD
