Metadata-Version: 2.4
Name: cmq
Version: 0.9.1
Summary: Cloud Multi Query is a library & CLI tool that allows you to run queries across multiple cloud accounts in parallel.
License-Expression: Apache-2.0
License-File: LICENSE
Author: Daniel Isla Cruz
Author-email: daniel.islacruz@ocado.com
Requires-Python: >=3.10,<4.0
Classifier: Programming Language :: Python :: 3
Classifier: Programming Language :: Python :: 3.10
Classifier: Programming Language :: Python :: 3.11
Classifier: Programming Language :: Python :: 3.12
Classifier: Programming Language :: Python :: 3.13
Classifier: Programming Language :: Python :: 3.14
Requires-Dist: atpbar (==2.0.4)
Requires-Dist: boto3 (>=1.34.80,<2.0.0)
Requires-Dist: click (>=8.1.7,<9.0.0)
Requires-Dist: matplotlib (>=3.9.0,<4.0.0)
Requires-Dist: python-benedict (>=0.33.2,<0.34.0)
Requires-Dist: requests (>=2.31.0,<3.0.0)
Requires-Dist: rich (>=13.7.1,<14.0.0)
Project-URL: Changelog, https://github.com/ocadotechnology/cmq/blob/main/CHANGELOG.md
Project-URL: Homepage, https://github.com/ocadotechnology/cmq
Project-URL: Issues, https://github.com/ocadotechnology/cmq/issues
Project-URL: Repository, https://github.com/ocadotechnology/cmq.git
